[
  {
    "@id": "https://carlamenegat.github.io/VarelaDigital/person/urbano_soares_silva",
    "http://xmlns.com/foaf/0.1/name": [
      {
        "@value": "Urbano Soares da Silva"
      }
    ]
  },
  {
    "@id": "https://www.geonames.org/3467512/cangucu.html",
    "http://www.w3.org/2000/01/rdf-schema#label": [
      {
        "@language": "pt-BR",
        "@value": "Canguçu"
      }
    ]
  },
  {
    "@id": "https://carlamenegat.github.io/VarelaDigital/assets/html/documents_html/CV-75.html",
    "@type": [
      "http://purl.org/dc/terms/FileFormat"
    ]
  },
  {
    "@id": "https://carlamenegat.github.io/VarelaDigital/doc/CV-75",
    "@type": [
      "http://purl.org/dc/terms/BibliographicResource"
    ],
    "http://purl.org/dc/terms/creator": [
      {
        "@id": "https://carlamenegat.github.io/VarelaDigital/person/francisco_pedro_abreu"
      }
    ],
    "http://purl.org/dc/terms/date": [
      {
        "@type": "http://www.w3.org/2001/XMLSchema#date",
        "@value": "1843-10-20"
      }
    ],
    "http://purl.org/dc/terms/hasFormat": [
      {
        "@id": "https://carlamenegat.github.io/VarelaDigital/letters_data/documents_XML/CV-75.xml"
      },
      {
        "@id": "https://carlamenegat.github.io/VarelaDigital/assets/html/documents_html/CV-75.html"
      }
    ],
    "http://purl.org/dc/terms/identifier": [
      {
        "@value": "CV-75"
      }
    ],
    "http://purl.org/dc/terms/relation": [
      {
        "@id": "https://carlamenegat.github.io/VarelaDigital/person/urbano_soares_silva"
      }
    ],
    "http://purl.org/dc/terms/spatial": [
      {
        "@id": "https://www.geonames.org/3467512/cangucu.html"
      }
    ],
    "http://purl.org/dc/terms/title": [
      {
        "@language": "pt-BR",
        "@value": "Carta CV-75 – Francisco Pedro de Abreu para Urbano Soares da Silva"
      }
    ],
    "http://purl.org/dc/terms/type": [
      {
        "@value": "letter"
      }
    ],
    "https://carlamenegat.github.io/VarelaDigital/hrao#addressedTo": [
      {
        "@id": "https://carlamenegat.github.io/VarelaDigital/person/urbano_soares_silva"
      }
    ]
  },
  {
    "@id": "https://carlamenegat.github.io/VarelaDigital/person/francisco_pedro_abreu",
    "http://xmlns.com/foaf/0.1/name": [
      {
        "@value": "Francisco Pedro de Abreu"
      }
    ]
  },
  {
    "@id": "https://carlamenegat.github.io/VarelaDigital/letters_data/documents_XML/CV-75.xml",
    "@type": [
      "http://purl.org/dc/terms/FileFormat"
    ]
  }
]