[
  {
    "@id": "https://www.geonames.org/3451632/restinga-seca.html",
    "http://www.w3.org/2000/01/rdf-schema#label": [
      {
        "@language": "pt-BR",
        "@value": "Restinga Seca"
      }
    ]
  },
  {
    "@id": "https://carlamenegat.github.io/VarelaDigital/person/antonio_correia_seara",
    "http://xmlns.com/foaf/0.1/name": [
      {
        "@value": "Antônio Correia Seara"
      }
    ]
  },
  {
    "@id": "https://carlamenegat.github.io/VarelaDigital/doc/CV-94",
    "@type": [
      "http://purl.org/dc/terms/BibliographicResource"
    ],
    "http://purl.org/dc/terms/creator": [
      {
        "@id": "https://carlamenegat.github.io/VarelaDigital/person/francisco_manuel_accioli"
      }
    ],
    "http://purl.org/dc/terms/date": [
      {
        "@type": "http://www.w3.org/2001/XMLSchema#date",
        "@value": "1841-12-08"
      }
    ],
    "http://purl.org/dc/terms/hasFormat": [
      {
        "@id": "https://carlamenegat.github.io/VarelaDigital/letters_data/documents_XML/CV-94.xml"
      },
      {
        "@id": "https://carlamenegat.github.io/VarelaDigital/assets/html/documents_html/CV-94.html"
      }
    ],
    "http://purl.org/dc/terms/identifier": [
      {
        "@value": "CV-94"
      }
    ],
    "http://purl.org/dc/terms/relation": [
      {
        "@id": "https://carlamenegat.github.io/VarelaDigital/person/antonio_correia_seara"
      }
    ],
    "http://purl.org/dc/terms/spatial": [
      {
        "@id": "https://www.geonames.org/3451632/restinga-seca.html"
      }
    ],
    "http://purl.org/dc/terms/title": [
      {
        "@language": "pt-BR",
        "@value": "Carta CV-94 – Francisco Manuel Accioli para Antônio Correia Seara"
      }
    ],
    "http://purl.org/dc/terms/type": [
      {
        "@value": "letter"
      }
    ],
    "https://carlamenegat.github.io/VarelaDigital/hrao#addressedTo": [
      {
        "@id": "https://carlamenegat.github.io/VarelaDigital/person/antonio_correia_seara"
      }
    ]
  },
  {
    "@id": "https://carlamenegat.github.io/VarelaDigital/letters_data/documents_XML/CV-94.xml",
    "@type": [
      "http://purl.org/dc/terms/FileFormat"
    ]
  },
  {
    "@id": "https://carlamenegat.github.io/VarelaDigital/assets/html/documents_html/CV-94.html",
    "@type": [
      "http://purl.org/dc/terms/FileFormat"
    ]
  },
  {
    "@id": "https://carlamenegat.github.io/VarelaDigital/person/francisco_manuel_accioli",
    "http://xmlns.com/foaf/0.1/name": [
      {
        "@value": "Francisco Manuel Accioli"
      }
    ]
  }
]